{
  "task_id": "b5948a4c-8dd8-4b4f-8acf-32c444e9b071",
  "run_id": "b772a983-73f8-4c02-b427-3ae59c83600f",
  "node_id": "persistent_node",
  "node_type": "DemoNode",
  "status": "pending",
  "started_at": null,
  "ended_at": null,
  "completed_at": null,
  "created_at": "2025-05-31T04:59:00.423804",
  "result": null,
  "error": null,
  "metadata": {
    "important_data": "This should persist"
  },
  "input_data": null,
  "output_data": null,
  "metrics": null,
  "dependencies": [],
  "parent_task_id": null,
  "retry_count": 0
}
